shannon_entropy
