Metadata-Version: 1.0
Name: shannon-entropy
Version: 0.2.1
Summary: Calculate the Shannon Entropy for an image.
Home-page: http://github.com/micahwalter/shannon_entropy
Author: Micah Walter
Author-email: micah@micahwalter.com
License: MIT
Platform: UNKNOWN
